makesite_liquidish/makesite.py
makesite_liquidish/serve.py
makesite_liquidish/watch.py
makesite_liquidish/example_site/_config.yml
makesite_liquidish/example_site/contact.html
makesite_liquidish/example_site/galleries.html
makesite_liquidish/example_site/gallery-data.json
makesite_liquidish/example_site/index.html
makesite_liquidish/example_site/layout.html
makesite_liquidish/example_site/style.css
makesite_liquidish-1.0.4.dist-info/METADATA
makesite_liquidish-1.0.4.dist-info/WHEEL
makesite_liquidish-1.0.4.dist-info/entry_points.txt
makesite_liquidish-1.0.4.dist-info/top_level.txt
makesite_liquidish-1.0.4.dist-info/RECORD
