Metadata-Version: 2.1
Name: makesite-liquidish
Version: 1.0.4
Summary: A 'makesite' script that can handle {% if %} and {% for %} blocks as well as {{ name }} expressions.
Author: Patrick Pfeifer
License: MIT
Project-URL: Source, https://github.com/Pfiver/makesite-liquidish
Project-URL: PyPi, https://pypi.org/project/makesite-liquidish/
Requires-Python: >=3.10
Requires-Dist: pyyaml
Requires-Dist: watchdog
Requires-Dist: livereload
Provides-Extra: dev_or_whatever
